ansys/api/platform/instancemanagement/__init__.py
ansys/api/platform/instancemanagement/_version.py
ansys/api/platform/instancemanagement/py.typed
ansys/api/platform/instancemanagement/v1/product_instance_manager.proto
ansys/api/platform/instancemanagement/v1/product_instance_manager_pb2.py
ansys/api/platform/instancemanagement/v1/product_instance_manager_pb2.pyi
ansys/api/platform/instancemanagement/v1/product_instance_manager_pb2_grpc.py
ansys/api/platform/instancemanagement/v1/product_instance_manager_pb2_grpc.pyi
ansys_api_platform_instancemanagement-1.1.3.dist-info/licenses/AUTHORS
ansys_api_platform_instancemanagement-1.1.3.dist-info/licenses/LICENSE
ansys_api_platform_instancemanagement-1.1.3.dist-info/METADATA
ansys_api_platform_instancemanagement-1.1.3.dist-info/WHEEL
ansys_api_platform_instancemanagement-1.1.3.dist-info/entry_points.txt
ansys_api_platform_instancemanagement-1.1.3.dist-info/top_level.txt
ansys_api_platform_instancemanagement-1.1.3.dist-info/RECORD
