Metadata-Version: 2.4
Name: ansys-api-platform-instancemanagement
Version: 1.1.3
Summary: Autogenerated python gRPC interface package for ansys-api-platform-instancemanagement, built on 11:17:24 on 11 April 2025
Home-page: https://github.com/ansys/ansys-api-platform-instancemanagement
Author: ANSYS, Inc.
Author-email: pyansys.core@ansys.com
License: MIT
Requires-Python: >=3.8
License-File: LICENSE
License-File: AUTHORS
Requires-Dist: grpcio~=1.17
Requires-Dist: protobuf<7,>=3.19
Dynamic: author
Dynamic: author-email
Dynamic: description
Dynamic: description-content-type
Dynamic: home-page
Dynamic: license
Dynamic: license-file
Dynamic: requires-dist
Dynamic: requires-python
Dynamic: summary
